pyskroutz/__init__.py
pyskroutz/client.py
pyskroutz/models/__init__.py
pyskroutz/models/base.py
pyskroutz/models/books.py
pyskroutz/models/categories.py
pyskroutz/models/favorites.py
pyskroutz/models/filters.py
pyskroutz/models/flags.py
pyskroutz/models/manufacturers.py
pyskroutz/models/notifications.py
pyskroutz/models/products.py
pyskroutz/models/search.py
pyskroutz/models/shops.py
pyskroutz/models/skus.py
pyskroutz/models/users.py
pyskroutz/resources/__init__.py
pyskroutz/resources/base.py
pyskroutz/resources/books.py
pyskroutz/resources/categories.py
pyskroutz/resources/favorites.py
pyskroutz/resources/filters.py
pyskroutz/resources/flags.py
pyskroutz/resources/manufacturers.py
pyskroutz/resources/notifications.py
pyskroutz/resources/products.py
pyskroutz/resources/search.py
pyskroutz/resources/shops.py
pyskroutz/resources/skus.py
pyskroutz/resources/users.py
pyskroutz/utils.py
pyskroutz-0.2.0.dist-info/LICENSE
pyskroutz-0.2.0.dist-info/METADATA
pyskroutz-0.2.0.dist-info/WHEEL
pyskroutz-0.2.0.dist-info/RECORD
