Metadata-Version: 2.1
Name: pyskroutz
Version: 0.2.0
Summary: A Python client for Skroutz API.
Home-page: https://github.com/sp1thas/pyskroutz
License: GPL-3.0-only
Keywords: skroutz,skroutz-api,api-client
Author: Panagiotis Simakis
Maintainer: Panagiotis Simakis
Requires-Python: >=3.7
Classifier: Development Status :: 4 - Beta
Classifier: Framework :: Pytest
Classifier: License :: OSI Approved :: GNU General Public License v3 (GPLv3)
Classifier: Natural Language :: English
Classifier: Natural Language :: Greek
Classifier: Operating System :: OS Independent
Classifier: Programming Language :: Python :: 3
Classifier: Programming Language :: Python :: 3.7
Classifier: Programming Language :: Python :: 3.8
Classifier: Programming Language :: Python :: 3.9
Classifier: Programming Language :: Python :: 3.10
Classifier: Programming Language :: Python :: 3.11
Classifier: Programming Language :: Python :: 3
Classifier: Programming Language :: Python :: 3.10
Classifier: Programming Language :: Python :: 3.6
Classifier: Programming Language :: Python :: 3.7
Classifier: Programming Language :: Python :: 3.8
Classifier: Programming Language :: Python :: 3.9
Classifier: Topic :: Software Development :: Libraries :: Python Modules
Requires-Dist: pydantic[email] (>=1.8.2,<2.0.0)
Requires-Dist: requests (>=2.25.1,<3.0.0)
Project-URL: Bug Tracker, https://github.com/sp1thas/pyskroutz/issues
Project-URL: Documentation, https://pyskroutz.simakis.me/en/latest/
Project-URL: Repository, https://github.com/sp1thas/pyskroutz
